mlflow_elasticsearchstore/__init__.py
mlflow_elasticsearchstore/_version.py
mlflow_elasticsearchstore/elasticsearch_store.py
mlflow_elasticsearchstore/models.py
mlflow_elasticsearchstore-0.1.2.dist-info/LICENSE
mlflow_elasticsearchstore-0.1.2.dist-info/METADATA
mlflow_elasticsearchstore-0.1.2.dist-info/WHEEL
mlflow_elasticsearchstore-0.1.2.dist-info/entry_points.txt
mlflow_elasticsearchstore-0.1.2.dist-info/top_level.txt
mlflow_elasticsearchstore-0.1.2.dist-info/RECORD
