Metadata-Version: 2.1
Name: mlflow-elasticsearchstore
Version: 0.1.2
Summary: Mlflow plugin to use ElasticSearch as backend for MLflow tracking service
Home-page: https://github.com/criteo/mlflow-elasticsearchstore
Maintainer: Criteo
Maintainer-email: github@criteo.com
License: UNKNOWN
Keywords: mlflow
Platform: UNKNOWN
Classifier: Development Status :: 4 - Beta
Classifier: Intended Audience :: Developers
Classifier: Intended Audience :: Science/Research
Classifier: Operating System :: POSIX :: Linux
Classifier: Environment :: Console
Classifier: License :: OSI Approved :: Apache Software License
Classifier: Programming Language :: Python :: 3
Classifier: Programming Language :: Python :: 3.6
Classifier: Programming Language :: Python :: 3.7
Classifier: Topic :: Software Development :: Libraries
Requires-Python: >=3.6
Requires-Dist: elasticsearch-dsl (<8.0.0,>=7.0.0)
Requires-Dist: mlflow
